{"pokemonId":322,"Type 1":10,"Type 2":5,"Attack":194,"Defense":139,"HP":140,"movesetsRanking":[{"APHAttacker":[],"APSAttacker":[],"potionDefender":[],"timeDefender":[]},{"APHAttacker":[],"APSAttacker":[],"potionDefender":[],"timeDefender":[]},{"APHAttacker":[],"APSAttacker":[],"potionDefender":[],"timeDefender":[]},{"APHAttacker":[],"APSAttacker":[],"potionDefender":[],"timeDefender":[]},{"APHAttacker":[],"APSAttacker":[],"potionDefender":[],"timeDefender":[]},{"APHAttacker":[],"APSAttacker":[],"potionDefender":[],"timeDefender":[]}]}