{"pokemonId":94,"Type 1":6,"Type 2":5,"Attack":85,"Defense":288,"HP":70,"movesetsRanking":[{"APLAttacker":[],"APSAttacker":[],"potionDefender":[],"timeDefender":[]},{"APLAttacker":[],"APSAttacker":[],"potionDefender":[],"timeDefender":[]},{"APLAttacker":[],"APSAttacker":[],"potionDefender":[],"timeDefender":[]},{"APLAttacker":[],"APSAttacker":[],"potionDefender":[],"timeDefender":[]},{"APLAttacker":[],"APSAttacker":[],"potionDefender":[],"timeDefender":[]},{"APLAttacker":[],"APSAttacker":[],"potionDefender":[],"timeDefender":[]},{"APLAttacker":[],"APSAttacker":[],"potionDefender":[],"timeDefender":[]},{"APLAttacker":[],"APSAttacker":[],"potionDefender":[],"timeDefender":[]}]}