{"pokemonId":45,"Type 1":7,"Type 2":12,"Attack":121,"Defense":99,"HP":70,"movesetsRanking":[{"APLAttacker":[],"APSAttacker":[],"potionDefender":[],"timeDefender":[]},{"APLAttacker":[],"APSAttacker":[],"potionDefender":[],"timeDefender":[]},{"APLAttacker":[],"APSAttacker":[],"potionDefender":[],"timeDefender":[]},{"APLAttacker":[],"APSAttacker":[],"potionDefender":[],"timeDefender":[]},{"APLAttacker":[],"APSAttacker":[],"potionDefender":[],"timeDefender":[]},{"APLAttacker":[],"APSAttacker":[],"potionDefender":[],"timeDefender":[]}]}