{"pokemonId":232,"Type 1":1,"Type 2":0,"Attack":198,"Defense":183,"HP":170,"movesetsRanking":[{"APHAttacker":[],"APSAttacker":[],"potionDefender":[],"timeDefender":[]},{"APHAttacker":[],"APSAttacker":[],"potionDefender":[],"timeDefender":[]},{"APHAttacker":[],"APSAttacker":[],"potionDefender":[],"timeDefender":[]},{"APHAttacker":[],"APSAttacker":[],"potionDefender":[],"timeDefender":[]},{"APHAttacker":[],"APSAttacker":[],"potionDefender":[],"timeDefender":[]},{"APHAttacker":[],"APSAttacker":[],"potionDefender":[],"timeDefender":[]}]}